{
  "$schema": "https://json-schema.org/draft/2020-12/schema",
  "$id": "https://raw.githubusercontent.com/api-evangelist/argo-workflows/refs/heads/main/json-schema/argo-workflows-github-com-argoproj-argo-events-pkg-apis-events-v1alpha1-slack-thread-schema.json",
  "title": "github.com.argoproj.argo_events.pkg.apis.events.v1alpha1.SlackThread",
  "description": "github.com.argoproj.argo_events.pkg.apis.events.v1alpha1.SlackThread schema from Argo Workflows API",
  "type": "object",
  "properties": {
    "broadcastMessageToChannel": {
      "type": "boolean",
      "title": "BroadcastMessageToChannel allows to also broadcast the message from the thread to the channel\n+optional"
    },
    "messageAggregationKey": {
      "type": "string",
      "title": "MessageAggregationKey allows to aggregate the messages to a thread by some key.\n+optional"
    }
  }
}